chris/__init__.py
chris/client.py
chris/cube/__init__.py
chris/cube/base_collection_links.py
chris/cube/feed.py
chris/cube/files.py
chris/cube/pipeline.py
chris/cube/piping.py
chris/cube/plugin.py
chris/cube/plugin_instance.py
chris/errors.py
chris/helpers/__init__.py
chris/helpers/collection.py
chris/helpers/connected_resource.py
chris/helpers/deserialize.py
chris/helpers/pagination.py
chris/helpers/peek.py
chris/types.py
chris/wait.py
caw-0.8.0.dist-info/LICENSE
caw-0.8.0.dist-info/WHEEL
caw-0.8.0.dist-info/METADATA
caw-0.8.0.dist-info/RECORD
