Metadata-Version: 2.1
Name: caw
Version: 0.8.0
Summary: ChRIS client library
Home-page: https://chrisproject.org
License: MIT
Author: FNNDSC
Author-email: dev@babyMRI.org
Requires-Python: >=3.8.2,<4.0.0
Classifier: License :: OSI Approved :: MIT License
Classifier: Programming Language :: Python :: 3
Classifier: Programming Language :: Python :: 3 :: Only
Classifier: Programming Language :: Python :: 3.10
Classifier: Programming Language :: Python :: 3.9
Classifier: Topic :: Scientific/Engineering :: Medical Science Apps.
Requires-Dist: click (>=8.1.2,<9.0.0)
Requires-Dist: pyserde (>=0.7.1,<0.8.0)
Requires-Dist: requests (>=2.27.1,<3.0.0)
Requires-Dist: typer (>=0.4.1,<0.5.0)
Project-URL: Documentation, https://fnndsc.github.io/caw
Project-URL: Repository, https://github.com/FNNDSC/caw
